[
  {
    "nome": "Dinofauro Game",
    "descricao": "Jogo simples em Python onde você controla um dinossauro e evita obstáculos.",
    "tecnologias": ["Python", "Pygame"],
    "github": "https://github.com/joopaulsl12/Dinofauro_game.py",
    "categoria": "automation",
    "posicao": {
      "x": 15,
      "y": 10
    }
  },
  {
    "nome": "Quebra-Cabeça",
    "descricao": "Jogo de quebra-cabeça simples para testar lógica e raciocínio.",
    "tecnologias": ["Python", "Tkinter"],
    "github": "https://github.com/joopaulsl12/quebra_cabeca",
    "categoria": "web",
    "posicao": {
      "x": 30,
      "y": 20
    }
  }
]
